<?xml version="1.0" encoding="utf-8" ?>
<entry_list version="1.0">
	<entry id="beam[1]"><ew>beam</ew><subj>PY-2b#TL-2c#NV-2c#TX-1b#IN-1d#WP-1a#AG-1c#AC-1e#NA-1e,f#ME-1g#AN-3#BD-1a,e#HF-3</subj><hw hindex="1">beam</hw><sound><wav>beam0001.wav</wav><wpr>!bEm</wpr></sound><pr>ˈbēm</pr><fl>noun</fl><et>Middle English <it>beem,</it> from Old English <it>bēam</it> tree, beam; akin to Old High German <it>boum</it> tree</et><def><date>before 12th century</date> <sn>1 a</sn> <dt>:a long piece of heavy often squared timber suitable for use in construction</dt>  <sn>b</sn> <dt>:a wood or metal cylinder in a loom on which the warp is wound</dt>  <sn>c</sn> <dt>:the part of a plow to which handles, standard, and coulter are attached</dt>  <sn>d</sn> <dt>:the bar of a balance from which scales hang</dt>  <sn>e</sn> <dt>:one of the principal horizontal supporting members (as of a building or ship) <vi>a steel <it>beam</it> supporting a floor</vi></dt> <sd>also</sd> <dt>:<sx>boom</sx> <sx>spar</sx> <vi>the <it>beam</it> of a crane</vi></dt>  <sn>f</sn> <dt>:the extreme width of a ship at the widest part</dt>  <sn>g</sn> <dt>:an oscillating lever on a central axis receiving motion at one end from an engine connecting rod and transmitting it at the other</dt> <sn>2 a</sn> <dt>:a ray or shaft of light</dt>  <sn>b</sn> <dt>:a collection of nearly parallel rays (as X rays) or a stream of particles (as electrons)</dt>  <sn>c</sn> <dt>:a constant directional radio signal transmitted for the guidance of pilots</dt> <sd>also</sd> <dt>:the course indicated by a radio beam</dt> <sn>3</sn> <dt>:the main stem of a deer's antler</dt> <sn>4</sn> <dt>:the width of the buttocks</dt></def><dro><drp>on the beam</drp> <def> <sn>1</sn> <dt>:following a guiding beam</dt> <sn>2</sn> <dt>:proceeding or operating correctly</dt></def></dro></entry>
	<entry id="beam[2]"><ew>beam</ew><subj>BD-vt2#BR-vt1#BR-vt3a#TL-vt1#TL-vt3#CP-vt3b</subj><hw hindex="2">beam</hw><fl>verb</fl><def><vt>transitive verb</vt><date>15th century</date> <sn>1</sn> <dt>:to emit in <fw>beams</fw> or as a beam</dt> <sn>2</sn> <dt>:to support with beams</dt> <sn>3 a</sn> <dt>:to transmit especially by satellite :<sx>broadcast</sx></dt>  <sn>b</sn> <dt>:to transmit (data) electronically</dt>  <sn>c</sn> <dt>:to direct to a particular audience</dt><vt>intransitive verb</vt> <sn>1</sn> <dt>:to send out beams of light</dt> <sn>2</sn> <dt>:to smile with joy</dt></def></entry>
	<entry id="beam-ends"><ew>beam-ends</ew><subj>NA</subj><hw>beam–ends</hw><sound><wav>beame01w.wav</wav><wpr>!bEm-!en(d)z</wpr></sound><pr>ˈbēm-ˈen(d)z</pr><fl>noun plural</fl><def><date>1750</date><dt>:the ends of a ship's beams</dt></def><dro><drp>on her beam–ends</drp> <def><dt>:inclined so much on one side that the beams approach a vertical position</dt></def></dro></entry>
	<entry id="beam sea"><ew>beam sea</ew><subj>NA</subj><hw>beam sea</hw><fl>noun</fl><def><date>1861</date><dt>:a sea whose surface motion is approximately at a right angle to the course of a vessel</dt></def></entry>
	<entry id="beam splitter"><ew>beam splitter</ew><subj>PY</subj><hw>beam splitter</hw><fl>noun</fl><def><date>1935</date><dt>:a mirror or prism or a combination of the two that is used to divide a beam of radiation into two or more parts</dt></def></entry>
	<entry id="balance beam"><ew>balance beam</ew><subj>SG</subj><hw>balance beam</hw><fl>noun</fl><def><date>circa 1949</date> <sn>1</sn> <dt>:a narrow wooden beam supported in a horizontal position approximately four feet above the floor and used for balancing feats in gymnastics</dt> <sn>2</sn> <dt>:an event in gymnastics competition in which the balance beam is used</dt></def></entry>
	<entry id="high beam"><ew>high beam</ew><subj>AV</subj><hw>high beam</hw><fl>noun</fl><def><date>1939</date><dt>:a vehicle headlight beam with a long-range focus</dt></def></entry>
	<entry id="I beam"><ew>I beam</ew><subj>BD</subj><hw>I beam</hw><fl>noun</fl><def><date>circa 1889</date><dt>:an iron or steel beam that is I-shaped in cross section</dt></def></entry>
	<entry id="low beam"><ew>low beam</ew><subj>AV</subj><hw>low beam</hw><fl>noun</fl><def><date>circa 1952</date><dt>:a vehicle headlight beam with a short-range focus</dt></def></entry>
	<entry id="sealed-beam"><ew>sealed-beam</ew><subj>AV</subj><hw>sealed–beam</hw><sound><wav>sealed01.wav</wav><wpr>!sE(u)l(d)-!bEm</wpr></sound><pr>ˈsēl(d)-ˈbēm</pr><fl>adjective</fl><def><date>1939</date><dt>:being an electric lamp with a prefocused reflector and lens sealed in the lamp vacuum</dt></def></entry>
</entry_list>