<?xml version="1.0" encoding="utf-8" ?>
<entry_list version="1.0">
	<entry id="behave"><ew>behave</ew><hw>be*have</hw><sound><wav>behave01.wav</wav><wpr>bi-!hAv</wpr></sound><pr>bi-ˈhāv, bē-</pr><fl>verb</fl><in><if>be*haved</if></in><in><if>be*hav*ing</if></in><et>Middle English <it>behaven,</it> from <it>be-</it> + <it>haven</it> to have, hold</et><def><vt>transitive verb</vt><date>15th century</date> <sn>1</sn> <dt>:to manage the actions of (oneself) in a particular way</dt> <sn>2</sn> <dt>:to conduct (oneself) in a proper manner</dt><vt>intransitive verb</vt> <sn>1</sn> <dt>:to act, function, or react in a particular way</dt> <sn>2</sn> <dt>:to conduct oneself properly</dt></def><uro><ure>be*hav*er</ure> <fl>noun</fl></uro><pl>syn</pl><pt><sc>behave</sc> <sc>conduct</sc> <sc>deport</sc> <sc>comport</sc> <sc>acquit</sc> mean to act or to cause oneself to do something in a certain way. <sc>behave</sc> may apply to the meeting of a standard of what is proper or decorous <vi>the children <it>behaved</it> in church</vi>. <sc>conduct</sc> implies action or behavior that shows the extent of one's power to control or direct oneself <vi><it>conducted</it> herself with unfailing good humor</vi>. <sc>deport</sc> implies behaving so as to show how far one conforms to conventional rules of discipline or propriety <vi>the hero <it>deported</it> himself in accord with the code of chivalry</vi>. <sc>comport</sc> suggests conduct measured by what is expected or required of one in a certain class or position <vi><it>comported</it> themselves as gentlemen</vi>. <sc>acquit</sc> applies to action under stress that deserves praise or meets expectations <vi><it>acquitted</it> herself well in her first assignment</vi>.</pt></entry>
</entry_list>