<?xml version="1.0" encoding="utf-8" ?>
<entry_list version="1.0">
	<entry id="cheer[1]"><ew>cheer</ew><hw hindex="1">cheer</hw><sound><wav>cheer001.wav</wav><wpr>!chir</wpr></sound><pr>ˈchir</pr><fl>noun</fl><et>Middle English <it>chere</it> face, cheer, from Anglo-French, face, from Medieval Latin <it>cara,</it> probably from Greek <it>kara</it> head, face <ma>cerebral</ma></et><def><date>13th century</date> <sn>1 a</sn> <ssl>obsolete</ssl> <dt>:<sx>face</sx></dt>  <sn>b</sn> <ssl>archaic</ssl> <dt>:facial expression</dt> <sn>2</sn> <dt>:state of mind or heart :<sx>spirit</sx> <vi>be of good <it>cheer</it> <aq>Matthew 9:2(Authorized Version)</aq></vi></dt> <sn>3</sn> <dt>:lightness of mind and feeling :<sx>animation</sx> <sx>gaiety</sx></dt> <sn>4</sn> <dt>:hospitable entertainment :<sx>welcome</sx></dt> <sn>5</sn> <dt>:food and drink for a feast :<sx>fare</sx></dt> <sn>6</sn> <dt>:something that gladdens <vi>words of <it>cheer</it></vi></dt> <sn>7</sn> <dt>:a shout of applause or encouragement</dt></def></entry>
	<entry id="cheer[2]"><ew>cheer</ew><hw hindex="2">cheer</hw><fl>verb</fl><def><vt>transitive verb</vt><date>14th century</date> <sn>1 a</sn> <dt>:to instill with hope or courage :<sx>comfort</sx> <un>usually used with <it>up</it></un></dt>  <sn>b</sn> <dt>:to make glad or happy <un>usually used with <it>up</it></un></dt> <sn>2</sn> <dt>:to urge on or encourage especially by shouts <vi><it>cheer</it><it>ed</it> the team on</vi></dt> <sn>3</sn> <dt>:to applaud with shouts</dt><vt>intransitive verb</vt> <sn>1</sn> <ssl>obsolete</ssl> <dt>:to be mentally or emotionally disposed</dt> <sn>2</sn> <dt>:to grow or be <fw>cheerful</fw> :<sx>rejoice</sx> <un>usually used with <it>up</it></un></dt> <sn>3</sn> <dt>:to utter a shout of applause or triumph</dt></def><uro><ure>cheer*er</ure> <fl>noun</fl></uro></entry>
	<entry id="Bronx cheer"><ew>Bronx cheer</ew><hw>Bronx cheer</hw><sound><wav>bronx01w.wav</wav><wpr>!br@N(k)s-!chir</wpr></sound><pr>ˈbräŋ(k)s-</pr><fl>noun</fl><et><it>Bronx,</it> borough of New York City</et><def><date>1924</date><dt>:<sx>raspberry <sxn>2</sxn></sx></dt></def></entry>
</entry_list>