<?xml version="1.0" encoding="utf-8" ?>
<entry_list version="1.0">
	<entry id="cultivate"><ew>cultivate</ew><subj>AG-1#AG-2a#AG-2b</subj><hw>cul*ti*vate</hw><sound><wav>cultiv04.wav</wav><wpr>!kul-tu-+vAt</wpr></sound><pr>ˈkəl-tə-ˌvāt</pr><fl>verb</fl><in><if>cul*ti*vat*ed</if></in><in><if>cul*ti*vat*ing</if></in><et>Medieval Latin <it>cultivatus,</it> past participle of <it>cultivare,</it> from <it>cultivus</it> cultivable, from Latin <it>cultus,</it> past participle of <it>colere</it></et><def><vt>transitive verb</vt><date>circa 1655</date> <sn>1</sn> <dt>:to prepare or prepare and use for the raising of crops</dt> <sd>also</sd> <dt>:to loosen or break up the soil about (growing plants)</dt> <sn>2 a</sn> <dt>:to foster the growth of <vi><it>cultivate</it> vegetables</vi></dt>  <sn>b</sn> <dt>:<sx>culture <sxn>2a</sxn></sx></dt>  <sn>c</sn> <dt>:to improve by labor, care, or study :<sx>refine</sx> <vi><it>cultivate</it> the mind</vi></dt> <sn>3</sn> <dt>:<sx>further</sx> <sx>encourage</sx> <vi><it>cultivate</it> the arts</vi></dt> <sn>4</sn> <dt>:to seek the society of :make friends with</dt></def><uro><ure>cul*ti*vat*able</ure><sound><wav>cultiv05.wav</wav><wpr>!kul-tu-+vA-tu-bul</wpr></sound> <pr>-ˌvā-tə-bəl</pr> <fl>adjective</fl></uro></entry>
</entry_list>