<?xml version="1.0" encoding="utf-8" ?>
<entry_list version="1.0">
	<entry id="flood[1]"><ew>flood</ew><subj>GE-1a#OG-2#EE-4#BB-1b</subj><hw hindex="1">flood</hw><sound><wav>flood001.wav</wav><wpr>!flud</wpr></sound><pr>ˈfləd</pr><fl>noun</fl><et>Middle English, from Old English <it>flōd;</it> akin to Old High German <it>fluot</it> flood, Old English <it>flōwan</it> to flow</et><def><date>before 12th century</date> <sn>1 a</sn> <dt>:a rising and overflowing of a body of water especially onto normally dry land</dt> <sd>also</sd> <dt>:a condition of overflowing <vi>rivers in <it>flood</it></vi></dt>  <sn>b</sn> <slb>capitalized</slb> <dt>:a flood described in the Bible as covering the earth in the time of Noah</dt> <sn>2</sn> <dt>:the flowing in of the tide</dt> <sn>3</sn> <dt>:an overwhelming quantity or volume</dt> <sd>also</sd> <dt>:a state of abundant flow or volume <un>often used in the phrase <it>in full flood</it> <vi>a debate in full <it>flood</it></vi></un></dt> <sn>4</sn> <dt>:<sx>floodlight</sx></dt></def></entry>
	<entry id="flood[2]"><ew>flood</ew><subj>AV-vt2b#ME-vt2b</subj><hw hindex="2">flood</hw><fl>verb</fl><def><vt>transitive verb</vt><date>1663</date> <sn>1</sn> <dt>:to cover with a flood :<sx>inundate</sx></dt> <sn>2 a</sn> <dt>:to fill abundantly or excessively <vi><it>flood</it> the market</vi></dt>  <sn>b</sn> <dt>:to supply an excess of fuel to (as an engine or its carburetor) so that engine operation is hampered</dt><vt>intransitive verb</vt> <sn>1</sn> <dt>:to pour forth, go, or come in a flood</dt> <sn>2</sn> <dt>:to become filled with a flood</dt></def><uro><ure>flood*er</ure> <fl>noun</fl></uro></entry>
	<entry id="flood tide"><ew>flood tide</ew><subj>OG-1</subj><hw>flood tide</hw><fl>noun</fl><def><date>1719</date> <sn>1</sn> <dt>:a rising tide</dt> <sn>2 a</sn> <dt>:an overwhelming quantity</dt>  <sn>b</sn> <dt>:a high point :<sx>peak</sx></dt></def></entry>
	<entry id="flash flood"><ew>flash flood</ew><subj>GE#AT</subj><hw>flash flood</hw><fl>noun</fl><def><date>1940</date><dt>:a local flood of great volume and short duration generally resulting from heavy rainfall in the immediate vicinity</dt></def><uro><ure>flash flood</ure> <fl>verb</fl></uro></entry>
</entry_list>