<?xml version="1.0" encoding="utf-8" ?>
<entry_list version="1.0">
	<entry id="numerous"><ew>numerous</ew><hw>nu*mer*ous</hw><sound><wav>numero05.wav</wav><wpr>!nU-mu-rus</wpr></sound><pr>ˈnüm-rəs, ˈnü-mə-; ˈnyüm-, ˈnyü-mə-</pr><fl>adjective</fl><et>Middle English, from Latin <it>numerosus,</it> from <it>numerus</it></et><def><date>15th century</date><dt>:consisting of great numbers of units or individuals <vi>born into a <it>numerous</it> family</vi></dt> <sd>also</sd> <dt>:<sx>many</sx> <vi>received <it>numerous</it> complaints</vi></dt></def><uro><ure>nu*mer*ous*ly</ure> <fl>adverb</fl></uro><uro><ure>nu*mer*ous*ness</ure> <fl>noun</fl></uro></entry>
</entry_list>