<?xml version="1.0" encoding="utf-8" ?>
<entry_list version="1.0">
	<entry id="once[1]"><ew>once</ew><hw hindex="1">once</hw><sound><wav>once0001.wav</wav><wpr>!wun(t)s</wpr></sound><pr>ˈwən(t)s</pr><fl>adverb</fl><et>Middle English <it>ones,</it> from genitive of <it>on</it> one</et><def><date>12th century</date> <sn>1</sn> <dt>:one time and no more <vi>rode a horse only <it>once</it></vi></dt> <sn>2</sn> <dt>:at any one time :under any circumstances :<sx>ever</sx> <vi>didn't <it>once</it> thank me</vi></dt> <sn>3</sn> <dt>:at some indefinite time in the past :<sx>formerly</sx> <vi>was <it>once</it> a booming mining town</vi></dt> <sn>4</sn> <dt>:by one degree of relationship <vi>first cousin <it>once</it> removed</vi></dt></def><dro><drp>once and for all</drp> <def> <sn>1</sn> <dt>:with finality :<sx>definitively</sx></dt> <sn>2</sn> <dt>:for the last time</dt></def></dro><dro><drp>once in a while</drp> <def><dt>:<sx>now and then</sx></dt></def></dro></entry>
	<entry id="once[2]"><ew>once</ew><hw hindex="2">once</hw><fl>noun</fl><def><date>13th century</date><dt>:one single time :one time at least <vi>please be on time this <it>once</it></vi></dt></def><dro><drp>at once</drp> <def> <sn>1</sn> <dt>:at the same time :<sx>simultaneously</sx></dt> <sn>2</sn> <dt>:<sx>immediately</sx></dt> <sn>3</sn> <dt>:<sx>both</sx> <vi><it>at once</it> funny and sad</vi></dt></def></dro></entry>
	<entry id="once[3]"><ew>once</ew><hw hindex="3">once</hw><fl>adjective</fl><def><date>1691</date><dt>:that once was :<sx>former</sx> <vi>a <it>once</it> successful actor</vi></dt></def></entry>
	<entry id="once[4]"><ew>once</ew><hw hindex="4">once</hw><fl>conjunction</fl><def><date>1761</date><dt>:at the moment when :<sx>as soon as</sx> <vi><it>once</it> she spoke, I recognized her</vi></dt></def></entry>
	<entry id="once-over"><ew>once-over</ew><hw>once–over</hw><sound><wav>onceov01.wav</wav><wpr>+wun(t)s-!O-vur</wpr></sound><pr>ˌwən(t)s-ˈō-vər, ˈwən(t)s-ˌ</pr><fl>noun</fl><def><date>1913</date><dt>:a swift examination or survey</dt> <sd>especially</sd> <dt>:a swift comprehensive appraising glance <vi>gave me the <it>once–over</it></vi></dt></def></entry>
	<entry id="once that"><ew>once that</ew><hw>once that</hw><fl>conjunction</fl><def><date>1874</date><dt>:<sx>once</sx></dt></def></entry>
	<entry id="once-over-lightly[1]"><hw>once-over-lightly[1]</hw><fl>teaser entry</fl></entry>
	<entry id="once-over-lightly[2]"><hw>once-over-lightly[2]</hw><fl>teaser entry</fl></entry>
</entry_list>