<?xml version="1.0" encoding="utf-8" ?>
<entry_list version="1.0">
	<entry id="pencil[1]"><ew>pencil</ew><subj>FA-1#FA-2#FA-3a#HH-3#RX-3b#FH-3b#MA-4</subj><hw hindex="1">pen*cil</hw><sound><wav>pencel01.wav</wav><wpr>!pen(t)-sul</wpr></sound><pr>ˈpen(t)-səl</pr><fl>noun</fl><et>Middle English <it>pensel,</it> from Anglo-French <it>pincel,</it> from Vulgar Latin <it>*penicellus,</it> alteration of Latin <it>penicillus,</it> diminutive of <it>peniculus</it> brush, from diminutive of <it>penis</it> tail, penis</et><def><date>14th century</date> <sn>1</sn> <dt>:an artist's brush</dt> <sn>2</sn> <dt>:an artist's individual skill or style</dt> <sn>3 a</sn> <dt>:an implement for writing, drawing, or marking consisting of or containing a slender cylinder or strip of a solid marking substance</dt>  <sn>b</sn> <dt>:a small medicated or cosmetic roll or stick for local applications</dt> <sn>4</sn> <dt>:a set of geometric objects each pair of which has a common property <vi>the lines in a plane through a point comprise a <it>pencil</it> of lines</vi></dt> <sn>5</sn> <dt>:something (as a beam of radiation) long and thin like a pencil</dt></def></entry>
	<entry id="pencil[2]"><ew>pencil</ew><subj>FA</subj><hw hindex="2">pencil</hw><fl>verb</fl><in><if>penciled</if> <il>or</il> <if>pencilled</if></in><in><if>pencil*ing</if> <il>or</il> <if>pencil*ling</if> <pr>-s(ə-)liŋ</pr></in><def><vt>transitive verb</vt><date>circa 1532</date> <sn>1</sn> <dt>:to paint, draw, write, or mark with a pencil</dt> <sn>2</sn> <dt>:to plan or designate tentatively <un>used with <it>in</it> <vi><it>pencil</it><it>ed</it> him in as the nominee</vi></un></dt></def></entry>
	<entry id="pencel"><ew>pencel</ew><subj>HE</subj><hw>pen*cel</hw><sound><wav>pencel01.wav</wav><wpr>!pen(t)-sul</wpr></sound><vr><vl>or</vl> <va>pen*cil</va> <sound><wav>pencel01.wav</wav><wpr>!pen(t)-sul</wpr></sound> <pr>ˈpen(t)-səl</pr></vr><fl>noun</fl><et>Middle English <it>pencel,</it> from Anglo-French <it>pencel, penuncel</it></et><def><date>13th century</date><dt>:<sx>pennoncel</sx></dt></def></entry>
	<entry id="pencil pusher"><ew>pencil pusher</ew><subj>BZ</subj><hw>pencil pusher</hw><fl>noun</fl><def><date>1881</date><dt>:a person who does predominantly paperwork</dt></def></entry>
	<entry id="blue pencil"><ew>blue pencil</ew><subj>PU</subj><hw>blue pencil</hw><fl>noun</fl><def><date>1886</date><dt>:a writing instrument used for editing</dt> <sd>also</sd> <dt>:the act or practice of blue-penciling</dt></def></entry>
	<entry id="blue-pencil"><ew>blue-pencil</ew><subj>PU</subj><hw>blue–pen*cil</hw><sound><wav>bluep01w.wav</wav><wpr>!blU-!pen(t)-sul</wpr></sound><pr>ˈblü-ˈpen(t)-səl</pr><fl>verb</fl><def><vt>transitive verb</vt><date>1888</date><dt>:to edit especially by shortening or deletion</dt></def><uro><ure>blue penciller</ure> <fl>noun</fl></uro></entry>
	<entry id="eyebrow pencil"><ew>eyebrow pencil</ew><subj>FH</subj><hw>eyebrow pencil</hw><fl>noun</fl><def><date>1881</date><dt>:a cosmetic pencil for the eyebrows</dt></def></entry>
	<entry id="grease pencil"><ew>grease pencil</ew><subj>HH</subj><hw>grease pencil</hw><fl>noun</fl><def><date>1944</date><dt>:a pencil in which the marking substance is pigment and grease</dt></def></entry>
	<entry id="lead pencil"><ew>lead pencil</ew><subj>HH</subj><hw>lead pencil</hw><sound><wav>leadpe01.wav</wav><wpr>!led-!pen(t)-sul</wpr></sound><pr>ˈled-</pr><fl>noun</fl><def><date>1688</date><dt>:a pencil using graphite as the marking material</dt></def></entry>
	<entry id="red-pencil"><ew>red-pencil</ew><subj>PU-2#GV-1</subj><hw>red–pen*cil</hw><sound><wav>redpen01.wav</wav><wpr>!red-+pen(t)-sul</wpr></sound><pr>ˈred-ˌpen(t)-səl</pr><fl>verb</fl><def><vt>transitive verb</vt><date>1946</date> <sn>1</sn> <dt>:<sx>censor</sx></dt> <sn>2</sn> <dt>:<sx>correct</sx> <sx>revise</sx></dt></def></entry>
</entry_list>