<?xml version="1.0" encoding="utf-8" ?>
<entry_list version="1.0">
	<entry id="reflect"><ew>reflect</ew><subj>PY-vt2#PY-vi1</subj><hw>re*flect</hw><sound><wav>reflec01.wav</wav><wpr>ri-!flekt</wpr></sound><pr>ri-ˈflekt</pr><fl>verb</fl><et>Middle English, from Latin <it>reflectere</it> to bend back, from <it>re-</it> + <it>flectere</it> to bend</et><def><vt>transitive verb</vt><date>15th century</date> <sn>1</sn> <ssl>archaic</ssl> <dt>:to turn into or away from a course :<sx>deflect</sx></dt> <sn>2</sn> <dt>:to prevent passage of and cause to change direction <vi>a mirror <it>reflect</it><it>s</it> light</vi></dt> <sn>3</sn> <dt>:to bend or fold back</dt> <sn>4</sn> <dt>:to give back or exhibit as an image, likeness, or outline :<sx>mirror</sx> <vi>the clouds were <it>reflect</it><it>ed</it> in the water</vi></dt> <sn>5</sn> <dt>:to bring or cast as a result <vi>his attitude <it>reflect</it><it>s</it> little credit on his judgment</vi></dt> <sn>6</sn> <dt>:to make manifest or apparent :<sx>show</sx> <vi>the painting <it>reflect</it><it>s</it> his artistic vision</vi> <vi>the pulse <it>reflect</it><it>s</it> the condition of the heart</vi></dt> <sn>7</sn> <dt>:<sx>realize</sx> <sx>consider</sx></dt><vt>intransitive verb</vt> <sn>1</sn> <dt>:to throw back light or sound</dt> <sn>2 a</sn> <dt>:to think quietly and calmly</dt>  <sn>b</sn> <dt>:to express a thought or opinion resulting from <fw>reflection</fw></dt> <sn>3 a</sn> <dt>:to tend to bring reproach or discredit <vi>an investigation that <it>reflect</it><it>s</it> on all the members of the department</vi></dt>  <sn>b</sn> <dt>:to bring about a specified appearance or characterization <vi>an act which <it>reflect</it><it>s</it> well on her</vi></dt>  <sn>c</sn> <dt>:to have a bearing or influence</dt><ss>think</ss></def></entry>
</entry_list>