<?xml version="1.0" encoding="utf-8" ?>
<entry_list version="1.0">
	<entry id="scissors"><ew>scissors</ew><subj>HH-1#SG-2a#SM-2b</subj><hw>scis*sors</hw><sound><wav>scisso03.wav</wav><wpr>!si-zurz</wpr></sound><pr>ˈsi-zərz</pr><fl>noun plural but singular or plural in construction</fl><et>Middle English <it>cisours, sisoures,</it> from Middle French <it>cisoires,</it> from Vulgar Latin <it>*caesorium</it> (singular) cutting instrument, from Latin <it>caedere</it> to cut</et><def><date>14th century</date> <sn>1</sn> <dt>:a cutting instrument having two blades whose cutting edges slide past each other</dt> <sn>2 a</sn> <dt>:a gymnastic feat in which the leg movements suggest the opening and closing of scissors</dt>  <sn>b</sn> <dt>:<sx>scissors hold</sx></dt></def></entry>
	<entry id="scissor[1]"><ew>scissor</ew><subj>HH</subj><hw hindex="1">scis*sor</hw><sound><wav>scisso01.wav</wav><wpr>!si-zur</wpr></sound><pr>ˈsi-zər</pr><fl>noun</fl><def><date>15th century</date><dt>:<sx>scissors</sx></dt></def></entry>
	<entry id="scissor[2]"><ew>scissor</ew><hw hindex="2">scissor</hw><fl>verb</fl><in><if>scis*sored</if></in><in><if>scis*sor*ing</if><sound><wav>scisso02.wav</wav><wpr>!si-zu-riN</wpr></sound> <pr>ˈsi-zə-riŋ, ˈsiz-riŋ</pr></in><def><vt>transitive verb</vt><date>1612</date><dt>:to cut, cut up, or cut off with <fw>scissors</fw> or shears <vi><it>scissor</it><it>ed</it> the paper into strips</vi></dt></def></entry>
	<entry id="scissors-and-paste"><ew>scissors-and-paste</ew><hw>scissors–and–paste</hw><fl>adjective</fl><def><date>1902</date><dt>:being a compilation rather than an effort of original and independent investigation</dt></def></entry>
	<entry id="scissors hold"><ew>scissors hold</ew><subj>SM</subj><hw>scissors hold</hw><fl>noun</fl><def><date>1909</date><dt>:a wrestling hold in which the legs are locked around the head or body of an opponent</dt></def></entry>
	<entry id="scissors kick"><ew>scissors kick</ew><subj>SR</subj><hw>scissors kick</hw><fl>noun</fl><def><date>circa 1930</date><dt>:a swimming kick used especially in sidestrokes in which the legs move like scissors</dt></def></entry>
</entry_list>