<?xml version="1.0" encoding="utf-8" ?>
<entry_list version="1.0">
	<entry id="steam[1]"><ew>steam</ew><subj>CH-2#ME-3a#NA-4a#TN-4b#EN-3a</subj><hw hindex="1">steam</hw><sound><wav>steam001.wav</wav><wpr>!stEm</wpr></sound><pr>ˈstēm</pr><fl>noun</fl><et>Middle English <it>stem,</it> from Old English <it>stēam;</it> akin to Dutch <it>stoom</it> steam</et><def><date>before 12th century</date> <sn>1</sn> <dt>:a vapor arising from a heated substance</dt> <sn>2 a</sn> <dt>:the invisible vapor into which water is converted when heated to the boiling point</dt>  <sn>b</sn> <dt>:the mist formed by the condensation on cooling of water vapor</dt> <sn>3 a</sn> <dt>:water vapor kept under pressure so as to supply energy for heating, cooking, or mechanical work</dt> <sd>also</sd> <dt>:the power so generated</dt>  <sn>b</sn> <dt>:active force :<sx>power</sx> <sx>momentum</sx> <vi>got there under his own <it>steam</it></vi> <vi>sales began to pick up <it>steam</it></vi></dt> <sd>also</sd> <dt>:normal force <vi>at full <it>steam</it></vi></dt>  <sn>c</sn> <dt>:pent-up emotional tension <vi>needed to let off a little <it>steam</it></vi></dt> <sn>4 a</sn> <dt>:<sx>steamer <sxn>2a</sxn></sx></dt>  <sn>b</sn> <dt>:travel by or a trip in a <fw>steamer</fw></dt></def></entry>
	<entry id="steam[2]"><ew>steam</ew><subj>FD-vt2</subj><hw hindex="2">steam</hw><fl>verb</fl><def><vt>transitive verb</vt><date>15th century</date> <sn>1</sn> <dt>:to give out as fumes :<sx>exhale</sx></dt> <sn>2</sn> <dt>:to apply steam to</dt> <sd>especially</sd> <dt>:to expose to the action of steam (as for softening or cooking)</dt><vt>intransitive verb</vt> <sn>1</sn> <dt>:to rise or pass off as vapor</dt> <sn>2</sn> <dt>:to give off steam or vapor</dt> <sn>3 a</sn> <dt>:to move or travel by the agency of steam</dt>  <sn>b</sn> <dt>:to move or proceed with energy or force</dt> <sn>4</sn> <dt>:to be angry :<sx>boil</sx> <vi><it>steam</it><it>ing</it> over the insult</vi></dt></def></entry>
	<entry id="steam boiler"><ew>steam boiler</ew><subj>ME</subj><hw>steam boiler</hw><fl>noun</fl><def><date>1805</date><dt>:a boiler for producing steam</dt></def></entry>
	<entry id="steam chest"><ew>steam chest</ew><subj>ME</subj><hw>steam chest</hw><fl>noun</fl><def><date>1797</date><dt>:the chamber from which steam is distributed to a cylinder of a steam engine</dt></def></entry>
	<entry id="steam engine"><ew>steam engine</ew><subj>ME</subj><hw>steam engine</hw><fl>noun</fl><def><date>1751</date><dt>:an engine driven or worked by steam</dt> <sd>specifically</sd> <dt>:a reciprocating engine having a piston driven in a closed cylinder by steam</dt></def></entry>
	<entry id="steam iron"><ew>steam iron</ew><subj>HH</subj><hw>steam iron</hw><fl>noun</fl><def><date>circa 1943</date><dt>:a pressing iron with a compartment holding water that is converted to steam by the iron's heat and emitted through the soleplate onto the fabric being pressed</dt></def></entry>
	<entry id="steam shovel"><ew>steam shovel</ew><subj>CE</subj><hw>steam shovel</hw><fl>noun</fl><def><date>1878</date><dt>:a power shovel operated by steam</dt> <sd>broadly</sd> <dt>:<sx>power shovel</sx></dt></def></entry>
	<entry id="steam table"><ew>steam table</ew><subj>FD</subj><hw>steam table</hw><fl>noun</fl><def><date>1849</date><dt>:a table having openings to hold containers of cooked food over steam or hot water circulating beneath them</dt></def></entry>
	<entry id="steam turbine"><ew>steam turbine</ew><subj>ME</subj><hw>steam turbine</hw><fl>noun</fl><def><date>1860</date><dt>:a turbine that is driven by the pressure of steam discharged at high velocity against the turbine vanes</dt></def></entry>
	<entry id="steam up"><ew>steam up</ew><hw>steam up</hw><fl>verb</fl><def><vt>transitive verb</vt><date>1922</date><dt>:to make angry or excited :<sx>arouse</sx></dt></def></entry>
</entry_list>