<?xml version="1.0" encoding="utf-8" ?>
<entry_list version="1.0">
	<entry id="supply[1]"><ew>supply</ew><subj>RC-vt3#PI-vt2d#AN-vt2d</subj><hw hindex="1">sup*ply</hw><sound><wav>supply01.wav</wav><wpr>su-!plI</wpr></sound><pr>sə-ˈplī</pr><fl>verb</fl><in><if>sup*plied</if></in><in><if>sup*ply*ing</if></in><et>Middle English <it>supplien</it> to complete, compensate for, from Middle French <it>soupplier,</it> from Latin <it>supplēre</it> to fill up, complete, raise (a military unit, crew) to its full complement, substitute, from <it>sub-</it> up + <it>plēre</it> to fill <ma>sub-, full</ma></et><def><vt>transitive verb</vt><date>14th century</date> <sn>1</sn> <dt>:to add as a <fw>supplement</fw></dt> <sn>2</sn> <set>Middle French <it>souploier,</it> alteration of <it>soupplier</it></set>  <sn>a</sn> <dt>:to provide for :<sx>satisfy</sx> <vi>laws by which the material wants of men are <it>supplied</it> <aq><it>Bulletin of Bates College</it></aq></vi></dt>  <sn>b</sn> <dt>:to make available for use :<sx>provide</sx> <vi><it>supplied</it> the necessary funds</vi></dt>  <sn>c</sn> <dt>:to satisfy the needs or wishes of</dt>  <sn>d</sn> <dt>:to furnish (organs, tissues, or cells) with a vital element (as blood or nerve fibers)</dt> <sn>3</sn> <dt>:to substitute for another in</dt> <sd>specifically</sd> <dt>:to serve as a supply in (a church or pulpit)</dt><vt>intransitive verb</vt> <dt>:to serve as a supply or substitute</dt></def><uro><ure>sup*pli*er</ure><sound><wav>supply02.wav</wav><wpr>su-!plI(-u)r</wpr></sound> <pr>-ˈplī(-ə)r</pr> <fl>noun</fl></uro></entry>
	<entry id="supply[2]"><ew>supply</ew><subj>RC-2b</subj><hw hindex="2">supply</hw><fl>noun</fl><in><il>plural</il> <if>supplies</if></in><def><date>15th century</date> <sn>1</sn> <ssl>obsolete</ssl> <dt>:<sx>assistance</sx> <sx>succor</sx></dt> <sn>2 a</sn> <ssl>obsolete</ssl> <dt>:<sx>reinforcements</sx> <un>often used in plural</un></dt>  <sn>b</sn> <dt>:a member of the clergy filling a vacant pulpit temporarily</dt>  <sn>c</sn> <dt>:the quantity or amount (as of a commodity) needed or available <vi>beer was in short <it>supply</it> in that hot weather <aq>Nevil Shute</aq></vi></dt>  <sn>d</sn> <dt>:<sx>provisions</sx> <sx>stores</sx> <un>usually used in plural</un></dt> <sn>3</sn> <dt>:the act or process of filling a want or need <vi>engaged in the <it>supply</it> of raw materials to industry</vi></dt> <sn>4</sn> <dt>:the quantities of goods or services offered for sale at a particular time or at one price</dt> <sn>5</sn> <dt>:something that maintains or constitutes a supply</dt></def></entry>
	<entry id="supple[1]"><ew>supple</ew><hw hindex="1">sup*ple</hw><sound><wav>supple01.wav</wav><wpr>!su-pul</wpr></sound><pr>ˈsə-pəl <it>also</it> ˈsü-</pr><fl>adjective</fl><in><if>sup*pler</if><sound><wav>supple02.wav</wav><wpr>!su-p(u-)lur</wpr></sound> <pr>-p(ə-)lər</pr></in><in><if>sup*plest</if><sound><wav>supple03.wav</wav><wpr>!su-p(u-)lust</wpr></sound> <pr>-p(ə-)ləst</pr></in><et>Middle English <it>souple,</it> from Anglo-French <it>suple,</it> from Latin <it>supplic-, supplex</it> entreating for mercy, supplicant, perhaps from <it>sub-</it> + <it>-plic-</it> (akin to <it>plicare</it> to fold) <ma>ply</ma></et><def><date>14th century</date> <sn>1 a</sn> <dt>:compliant often to the point of obsequiousness</dt>  <sn>b</sn> <dt>:readily adaptable or responsive to new situations</dt> <sn>2 a</sn> <dt>:capable of being bent or folded without creases, cracks, or breaks :<sx>pliant</sx> <vi><it>supple</it> leather</vi></dt>  <sn>b</sn> <dt>:able to perform bending or twisting movements with ease :<sx>limber</sx> <vi><it>supple</it> legs of a dancer</vi></dt>  <sn>c</sn> <dt>:easy and fluent without stiffness or awkwardness <vi>sang with a lively, <it>supple</it> voice <aq>Douglas Watt</aq></vi></dt><ss>elastic</ss></def><uro><ure>sup*ple*ly</ure><sound><wav>supple06.wav</wav><wpr>!su-pu(l)-lE</wpr></sound> <pr>-pə(l)-lē</pr> <vr><vl>or</vl> <va>sup*ply</va> <sound><wav>supple04.wav</wav><wpr>!su-p(u-)lE</wpr></sound> <pr>-p(ə-)lē</pr></vr> <fl>adverb</fl></uro><uro><ure>sup*ple*ness</ure><sound><wav>supple07.wav</wav><wpr>!su-pul-nus</wpr></sound> <pr>-pəl-nəs</pr> <fl>noun</fl></uro></entry>
	<entry id="supply-side"><ew>supply-side</ew><subj>EC</subj><hw>sup*ply–side</hw><sound><wav>supply03.wav</wav><wpr>su-!plI-!sId</wpr></sound><pr>sə-ˈplī-ˈsīd</pr><fl>adjective</fl><def><date>1976</date><dt>:of, relating to, or being an economic theory that reduction of tax rates encourages more earnings, savings, and investment and thereby expands economic activity and the total taxable national income</dt></def><uro><ure>sup*ply–sid*er</ure><sound><wav>supply04.wav</wav><wpr>su-!plI-!sI-dur</wpr></sound> <pr>-ˈsī-dər</pr> <fl>noun</fl></uro></entry>
	<entry id="money supply"><ew>money supply</ew><subj>EC</subj><hw>money supply</hw><fl>noun</fl><def><date>1878</date><dt>:the total amount of money available in an economy for spending as calculated by any of various methods (as by adding total currency to funds available in private checking accounts)</dt></def></entry>
	<entry id="water supply"><ew>water supply</ew><subj>CE</subj><hw>water supply</hw><fl>noun</fl><def><date>1849</date><dt>:a source, means, or process of supplying water (as for a community) usually including reservoirs, tunnels, and pipelines</dt></def></entry>
</entry_list>