<?xml version="1.0" encoding="utf-8" ?>
<entry_list version="1.0">
	<entry id="wonder[1]"><ew>wonder</ew><hw hindex="1">won*der</hw><sound><wav>wonder01.wav</wav><wpr>!wun-dur</wpr></sound><pr>ˈwən-dər</pr><fl>noun</fl><et>Middle English, from Old English <it>wundor;</it> akin to Old High German <it>wuntar</it> wonder</et><def><date>before 12th century</date> <sn>1 a</sn> <dt>:a cause of astonishment or admiration :<sx>marvel</sx> <vi>it's a <it>wonder</it> you weren't killed</vi> <vi>the pyramid is a <it>wonder</it> to behold</vi></dt>  <sn>b</sn> <dt>:<sx>miracle</sx></dt> <sn>2</sn> <dt>:the quality of exciting amazed admiration</dt> <sn>3 a</sn> <dt>:rapt attention or astonishment at something awesomely mysterious or new to one's experience</dt>  <sn>b</sn> <dt>:a feeling of doubt or uncertainty</dt></def></entry>
	<entry id="wonder[2]"><ew>wonder</ew><hw hindex="2">wonder</hw><fl>verb</fl><in><if>won*dered</if></in><in><if>won*der*ing</if><sound><wav>wonder09.wav</wav><wpr>!wun-d(u-)riN</wpr></sound> <pr>-d(ə-)riŋ</pr></in><def><vt>intransitive verb</vt><date>before 12th century</date> <sn>1 a</sn> <dt>:to be in a state of wonder</dt>  <sn>b</sn> <dt>:to feel surprise</dt> <sn>2</sn> <dt>:to feel curiosity or doubt <vi><it>wonder</it><it>ing</it> about the future</vi></dt><vt>transitive verb</vt> <dt>:to be curious or in doubt about <vi><it>wonder</it><it>s</it> why birds sing</vi></dt></def><uro><ure>won*der*er</ure><sound><wav>wonder02.wav</wav><wpr>!wun-dur-ur</wpr></sound> <pr>-dər-ər</pr> <fl>noun</fl></uro></entry>
	<entry id="wonder[3]"><ew>wonder</ew><hw hindex="3">wonder</hw><fl>adjective</fl><def><date>12th century</date><dt> :<sx>wondrous</sx> <sx>wonderful</sx>: as</dt>  <sn>a</sn> <dt>:exciting amazement or admiration <vi><it>wonder</it> toys</vi></dt>  <sn>b</sn> <dt>:effective or efficient far beyond anything previously known or anticipated <vi>a <it>wonder</it> fabric</vi> </dt></def></entry>
	<entry id="Wonder"><ew>Wonder</ew><hw>Won*der</hw><sound><wav>wonder01.wav</wav></sound><pr>ˈwən-dər</pr><fl>biographical name</fl><def><dt>Stevie 1950–     born <it>Stevland Hardaway Judkins</it> Am. singer, songwriter &amp; instrumentalist</dt></def></entry>
	<entry id="wonder drug"><ew>wonder drug</ew><subj>RX</subj><hw>wonder drug</hw><fl>noun</fl><def><date>1939</date><dt>:<sx>miracle drug</sx></dt></def></entry>
	<entry id="wonder-worker"><ew>wonder-worker</ew><hw>won*der–work*er</hw><sound><wav>wonder09.wav</wav><wpr>!wun-dur-+wur-kur</wpr></sound><pr>-ˌwər-kər</pr><fl>noun</fl><def><date>1599</date><dt>:one that performs wonders</dt></def></entry>
	<entry id="wonder-working"><ew>wonder-working</ew><hw>won*der–work*ing</hw><sound><wav>wonder10.wav</wav><wpr>!wun-dur-+wur-kiN</wpr></sound><pr>-kiŋ</pr><fl>adjective</fl><def><date>1593</date><dt>:producing wonders</dt></def></entry>
	<entry id="boy wonder"><ew>boy wonder</ew><hw>boy wonder</hw><fl>noun</fl><def><date>1925</date><dt>:a young man of noteworthy achievements</dt></def></entry>
	<entry id="nine days' wonder"><ew>nine days' wonder</ew><grp>nine days'</grp><grp>nine wonder</grp><grp>days' wonder</grp><hw>nine days' wonder</hw><fl>noun</fl><def><date>1594</date><dt>:something or someone that creates a short-lived sensation <ca>called also <cat>nine day wonder</cat></ca></dt></def></entry>
</entry_list>